jf_pygments/__init__.py
jf_pygments/lexers/sql.py
jf_pygments/styles/baldr.py
jf_pygments/styles/white.py
jf_pygments-0.3.0.dist-info/METADATA
jf_pygments-0.3.0.dist-info/LICENSE
jf_pygments-0.3.0.dist-info/WHEEL
jf_pygments-0.3.0.dist-info/entry_points.txt
jf_pygments-0.3.0.dist-info/RECORD
